shield_das/__init__.py
shield_das/_version.py
shield_das/analysis.py
shield_das/data_plotter.py
shield_das/data_recorder.py
shield_das/helpers.py
shield_das/pressure_gauge.py
shield_das/thermocouple.py
shield_das/assets/delete.svg
shield_das/assets/download.svg
shield_das/assets/shield.svg
shield_das-0.3.1.dist-info/licenses/LICENSE
shield_das-0.3.1.dist-info/METADATA
shield_das-0.3.1.dist-info/WHEEL
shield_das-0.3.1.dist-info/top_level.txt
shield_das-0.3.1.dist-info/RECORD
