Metadata-Version: 2.4
Name: SHIELD_DAS
Version: 0.3.1
Summary: SHIELD permeation rig data aquisition system
Author: James Dark
Author-email: darkj385@mit.edu
License: MIT License
Project-URL: Homepage, https://github.com/PTTEPxMIT/SHIELD_DAS
Project-URL: Issues, https://github.com/PTTEPxMIT/SHIELD_DAS/issues
Classifier: Natural Language :: English
Classifier: Topic :: Scientific/Engineering
Classifier: Programming Language :: Python :: 3.9
Classifier: Programming Language :: Python :: 3.10
Classifier: Programming Language :: Python :: 3.11
Classifier: Programming Language :: Python :: 3.12
Classifier: Programming Language :: Python :: 3.13
Classifier: License :: OSI Approved :: Apache Software License
Classifier: Operating System :: OS Independent
Requires-Python: >=3.9
License-File: LICENSE
Requires-Dist: LabJackPython
Requires-Dist: numpy
Requires-Dist: dash
Requires-Dist: dash_bootstrap_components
Requires-Dist: pandas
Requires-Dist: keyboard
Requires-Dist: plotly-resampler
Requires-Dist: h-transport-materials
Requires-Dist: uncertainties
Provides-Extra: test
Requires-Dist: pytest; extra == "test"
Requires-Dist: pytest-cov; extra == "test"
Requires-Dist: numpy; extra == "test"
Provides-Extra: lint
Requires-Dist: ruff; extra == "lint"
Requires-Dist: mypy; extra == "lint"
Provides-Extra: docs
Requires-Dist: sphinx; extra == "docs"
Requires-Dist: sphinx-book-theme; extra == "docs"
Requires-Dist: sphinx-design; extra == "docs"
Requires-Dist: matplotlib; extra == "docs"
Dynamic: license-file
